django_admin/__init__.py
django_admin/djadmin.py
django_admin/templates/admin/addonly_form.html
django_admin/templates/admin/addonly_submit_line.html
django_admin/templates/admin/deleteonly_form.html
django_admin/templates/admin/deleteonly_submit_line.html
django_admin/templates/admin/readonly_form.html
django_admin/templatetags/__init__.py
django_admin/templatetags/djadmin_modify.py
django_admin-2.0.2.dist-info/METADATA
django_admin-2.0.2.dist-info/WHEEL
django_admin-2.0.2.dist-info/top_level.txt
django_admin-2.0.2.dist-info/RECORD
