Metadata-Version: 2.1
Name: django-admin
Version: 2.0.2
Summary: Django Admin Extensions
Home-page: https://github.com/django-xxx/django-admin
Author: Hackathon
Author-email: kimi.huang@brightcells.com
Keywords: Django Admin Extensions
Classifier: Development Status :: 5 - Production/Stable
Classifier: Environment :: Web Environment
Classifier: Framework :: Django
Classifier: Intended Audience :: Developers
Classifier: Programming Language :: Python
Classifier: Topic :: Software Development :: Libraries :: Python Modules
Classifier: Topic :: Office/Business :: Financial :: Spreadsheet
